triathlon_project/__init__.py
triathlon_project/analysis.py
triathlon_project/cleaning.py
triathlon_project/streamlit_app.py
triathlon_project-0.1.0.dist-info/WHEEL
triathlon_project-0.1.0.dist-info/METADATA
triathlon_project-0.1.0.dist-info/RECORD
